ufcpy/Champion.py
ufcpy/Fighter.py
ufcpy/__init__.py
ufcpy/core.py
ufcpy/exceptions.py
ufcpy/utils.py
ufcpy-3.0.0.dist-info/METADATA
ufcpy-3.0.0.dist-info/WHEEL
ufcpy-3.0.0.dist-info/top_level.txt
ufcpy-3.0.0.dist-info/RECORD
