Metadata-Version: 2.1
Name: ufcpy
Version: 3.0.0
Summary: A fast and easy way to access the UFC roster
Home-page: https://github.com/YoungTrep/ufcpy
Author: youngtrep
Author-email: youngtrep.business@gmail.com
License: MIT
Keywords: ufc,mma,mixed martial arts,fighting,fighters,ufc-api,mma-api
Classifier: Development Status :: 4 - Beta
Classifier: Environment :: Console
Classifier: Intended Audience :: Developers
Classifier: License :: OSI Approved :: MIT License
Classifier: Natural Language :: English
Classifier: Operating System :: OS Independent
Classifier: Programming Language :: Python :: 3
Classifier: Topic :: Internet :: WWW/HTTP :: Indexing/Search
Classifier: Topic :: Utilities
Classifier: Topic :: Software Development :: Libraries :: Python Modules
Requires-Python: >=3.8
Requires-Dist: beautifulsoup4>=4.12.3
Requires-Dist: requests>=2.32.3
Requires-Dist: lxml>=5.3.0
